RNASQLite/__init__.py
RNASQLite/cli.py
RNASQLite/db_utils.py
RNASQLite/gene_info.csv
RNASQLite/process_file.py
RNASQLite-0.1.9.dist-info/METADATA
RNASQLite-0.1.9.dist-info/WHEEL
RNASQLite-0.1.9.dist-info/entry_points.txt
RNASQLite-0.1.9.dist-info/top_level.txt
RNASQLite-0.1.9.dist-info/RECORD
