Metadata-Version: 2.1
Name: RNASQLite
Version: 0.1.9
Summary: A tool for managing RNA-Seq data with SQLite
Home-page: https://github.com/yourusername/RNASQLite
Author: Your Name
Author-email: your.email@example.com
Classifier: Programming Language :: Python :: 3
Classifier: License :: OSI Approved :: MIT License
Classifier: Operating System :: OS Independent
Requires-Python: >=3.6
Requires-Dist: pandas
